hss/__init__.py
hss/__main__.py
hss_brunorosilva-0.0.1.dist-info/LICENSE.txt
hss_brunorosilva-0.0.1.dist-info/METADATA
hss_brunorosilva-0.0.1.dist-info/WHEEL
hss_brunorosilva-0.0.1.dist-info/entry_points.txt
hss_brunorosilva-0.0.1.dist-info/top_level.txt
hss_brunorosilva-0.0.1.dist-info/RECORD
