Metadata-Version: 2.1
Name: hss-brunorosilva
Version: 0.0.1
Summary: command line interface for setting up streamlit webapps on heroku
Home-page: https://github.com/brunorosilva/heroku-streamlit-setup
Author: Bruno Rodrigues Silva
Author-email: rodriguessilvabruno@outlook.com
License: UNKNOWN
Platform: UNKNOWN
Classifier: Programming Language :: Python :: 3
Classifier: License :: OSI Approved :: MIT License
Classifier: Operating System :: OS Independent
Requires-Python: >=3.6
